decryptogame/__init__.py
decryptogame/components.py
decryptogame/end_criteria.py
decryptogame/game.py
decryptogame/generators.py
decryptogame/play.py
decryptogame/teams.py
decryptogame/official_words/english.py
decryptogame-1.1.1.dist-info/LICENSE
decryptogame-1.1.1.dist-info/METADATA
decryptogame-1.1.1.dist-info/WHEEL
decryptogame-1.1.1.dist-info/top_level.txt
decryptogame-1.1.1.dist-info/RECORD
