Metadata-Version: 2.1
Name: decryptogame
Version: 1.1.1
Summary: A non-official implementation of a Decrypto-style game for simulation and AI work.
Author-email: Jaden Rodriguez <jadenrodriguez7@gmail.com>
Project-URL: Homepage, https://github.com/YaBoiSkinnyP/decryptogame/
Classifier: Programming Language :: Python :: 3
Classifier: License :: OSI Approved :: GNU Affero General Public License v3 or later (AGPLv3+)
Classifier: Operating System :: OS Independent
Classifier: Development Status :: 4 - Beta
Requires-Python: >=3.10
License-File: LICENSE
